ttyg_evaluation/__init__.py
ttyg_evaluation/evaluation.py
ttyg_evaluation/sparql_results_comparison.py
ttyg_evaluation/tools_calls_comparison.py
ttyg_evaluation-3.0.0.dist-info/LICENSE
ttyg_evaluation-3.0.0.dist-info/METADATA
ttyg_evaluation-3.0.0.dist-info/WHEEL
ttyg_evaluation-3.0.0.dist-info/RECORD
