Metadata-Version: 2.3
Name: ttyg-evaluation
Version: 3.0.0
Summary: Talk to Your Graph (TTYG) Evaluation is a Python module for evaluating whether LLM agents correctly orchestrate and invoke available tools to answer user questions, based on a Q&A dataset with tool call expectations.
License: Apache-2.0
Requires-Python: >=3.12,<3.13
Classifier: License :: OSI Approved :: Apache Software License
Classifier: Programming Language :: Python :: 3
Classifier: Programming Language :: Python :: 3.12
Project-URL: Repository, https://github.com/Ontotext-AD/ttyg-evaluation
